[{"username":"harkirat@gmail.com","password":"123456"},{"username":"anshul@gmail.com","password":"anshultomar"},{"username":"anshuewl@gmail.com","password":"anshultomar"},{"username":"asdfads","password":"asdfs"},{"username":"asdfadsf","password":"asdfs"},{"username":"asdfadsf@gmail.com","password":"asdfs"},{"username":"asdfad3sf@gmail.com","password":"asdfs23"},{"username":"ansh@gmai.com","password":"abksjfhdfs"},{"username":"ansh@gmail.com","password":"abksjfhdfs"},{"username":"anshult@gmail.com","password":"1234"},{"username":"an@gmail.com","password":"1235412"},{"username":"anshl@gmail.com","password":"1234jnlsjdbfa"},{"username":"anshultom@gmail.com","password":"kqwjrhdhf"},{"username":"rwefwer@gmail.com","password":"qwterf"},{"username":"anshuu@gmail.com","password":"qsdaf"}]